{
    "storage": [
      {
        "astId": 121,
        "contract": "contracts/1_Storage.sol:Account",
        "label": "s",
        "offset": 0,
        "slot": "0",
        "type": "t_struct(AppStorage)684_storage"
      }
    ],
    "types": {
      "t_address": {
        "encoding": "inplace",
        "label": "address",
        "numberOfBytes": "20"
      },
      "t_array(t_bytes32)144_storage": {
        "base": "t_bytes32",
        "encoding": "inplace",
        "label": "bytes32[144]",
        "numberOfBytes": "4608"
      },
      "t_array(t_bytes4)dyn_storage": {
        "base": "t_bytes4",
        "encoding": "dynamic_array",
        "label": "bytes4[]",
        "numberOfBytes": "32"
      },
      "t_array(t_int8)32_storage": {
        "base": "t_int8",
        "encoding": "inplace",
        "label": "int8[32]",
        "numberOfBytes": "32"
      },
      "t_array(t_struct(FacetCut)91_storage)dyn_storage": {
        "base": "t_struct(FacetCut)91_storage",
        "encoding": "dynamic_array",
        "label": "struct IDiamondCut.FacetCut[]",
        "numberOfBytes": "32"
      },
      "t_array(t_struct(WhitelistStatus)356_storage)dyn_storage": {
        "base": "t_struct(WhitelistStatus)356_storage",
        "encoding": "dynamic_array",
        "label": "struct Storage.WhitelistStatus[]",
        "numberOfBytes": "32"
      },
      "t_array(t_uint256)14_storage": {
        "base": "t_uint256",
        "encoding": "inplace",
        "label": "uint256[14]",
        "numberOfBytes": "448"
      },
      "t_array(t_uint256)2_storage": {
        "base": "t_uint256",
        "encoding": "inplace",
        "label": "uint256[2]",
        "numberOfBytes": "64"
      },
      "t_array(t_uint32)dyn_storage": {
        "base": "t_uint32",
        "encoding": "dynamic_array",
        "label": "uint32[]",
        "numberOfBytes": "32"
      },
      "t_bool": {
        "encoding": "inplace",
        "label": "bool",
        "numberOfBytes": "1"
      },
      "t_bytes1": {
        "encoding": "inplace",
        "label": "bytes1",
        "numberOfBytes": "1"
      },
      "t_bytes32": {
        "encoding": "inplace",
        "label": "bytes32",
        "numberOfBytes": "32"
      },
      "t_bytes4": {
        "encoding": "inplace",
        "label": "bytes4",
        "numberOfBytes": "4"
      },
      "t_bytes_storage": {
        "encoding": "bytes",
        "label": "bytes",
        "numberOfBytes": "32"
      },
      "t_contract(IERC20)77": {
        "encoding": "inplace",
        "label": "contract IERC20",
        "numberOfBytes": "20"
      },
      "t_enum(FacetCutAction)82": {
        "encoding": "inplace",
        "label": "enum IDiamondCut.FacetCutAction",
        "numberOfBytes": "1"
      },
      "t_int24": {
        "encoding": "inplace",
        "label": "int24",
        "numberOfBytes": "3"
      },
      "t_int256": {
        "encoding": "inplace",
        "label": "int256",
        "numberOfBytes": "32"
      },
      "t_int8": {
        "encoding": "inplace",
        "label": "int8",
        "numberOfBytes": "1"
      },
      "t_int96": {
        "encoding": "inplace",
        "label": "int96",
        "numberOfBytes": "12"
      },
      "t_mapping(t_address,t_bool)": {
        "encoding": "mapping",
        "key": "t_address",
        "label": "mapping(address => bool)",
        "numberOfBytes": "32",
        "value": "t_bool"
      },
      "t_mapping(t_address,t_bytes_storage)": {
        "encoding": "mapping",
        "key": "t_address",
        "label": "mapping(address => bytes)",
        "numberOfBytes": "32",
        "value": "t_bytes_storage"
      },
      "t_mapping(t_address,t_mapping(t_address,t_bool))": {
        "encoding": "mapping",
        "key": "t_address",
        "label": "mapping(address => mapping(address => bool))",
        "numberOfBytes": "32",
        "value": "t_mapping(t_address,t_bool)"
      },
      "t_mapping(t_address,t_mapping(t_address,t_uint256))": {
        "encoding": "mapping",
        "key": "t_address",
        "label": "mapping(address => mapping(address => uint256))",
        "numberOfBytes": "32",
        "value": "t_mapping(t_address,t_uint256)"
      },
      "t_mapping(t_address,t_mapping(t_contract(IERC20)77,t_uint256))": {
        "encoding": "mapping",
        "key": "t_address",
        "label": "mapping(address => mapping(contract IERC20 => uint256))",
        "numberOfBytes": "32",
        "value": "t_mapping(t_contract(IERC20)77,t_uint256)"
      },
      "t_mapping(t_address,t_mapping(t_uint32,t_struct(Deposit)151_storage))": {
        "encoding": "mapping",
        "key": "t_address",
        "label": "mapping(address => mapping(uint32 => struct Account.Deposit))",
        "numberOfBytes": "32",
        "value": "t_mapping(t_uint32,t_struct(Deposit)151_storage)"
      },
      "t_mapping(t_address,t_mapping(t_uint32,t_uint256))": {
        "encoding": "mapping",
        "key": "t_address",
        "label": "mapping(address => mapping(uint32 => uint256))",
        "numberOfBytes": "32",
        "value": "t_mapping(t_uint32,t_uint256)"
      },
      "t_mapping(t_address,t_struct(AssetSilo)346_storage)": {
        "encoding": "mapping",
        "key": "t_address",
        "label": "mapping(address => struct Storage.AssetSilo)",
        "numberOfBytes": "32",
        "value": "t_struct(AssetSilo)346_storage"
      },
      "t_mapping(t_address,t_struct(Deposited)490_storage)": {
        "encoding": "mapping",
        "key": "t_address",
        "label": "mapping(address => struct Storage.Deposited)",
        "numberOfBytes": "32",
        "value": "t_struct(Deposited)490_storage"
      },
      "t_mapping(t_address,t_struct(MowStatus)169_storage)": {
        "encoding": "mapping",
        "key": "t_address",
        "label": "mapping(address => struct Account.MowStatus)",
        "numberOfBytes": "32",
        "value": "t_struct(MowStatus)169_storage"
      },
      "t_mapping(t_address,t_struct(SiloSettings)464_storage)": {
        "encoding": "mapping",
        "key": "t_address",
        "label": "mapping(address => struct Storage.SiloSettings)",
        "numberOfBytes": "32",
        "value": "t_struct(SiloSettings)464_storage"
      },
      "t_mapping(t_address,t_struct(State)263_storage)": {
        "encoding": "mapping",
        "key": "t_address",
        "label": "mapping(address => struct Account.State)",
        "numberOfBytes": "32",
        "value": "t_struct(State)263_storage"
      },
      "t_mapping(t_address,t_struct(TwaReserves)484_storage)": {
        "encoding": "mapping",
        "key": "t_address",
        "label": "mapping(address => struct Storage.TwaReserves)",
        "numberOfBytes": "32",
        "value": "t_struct(TwaReserves)484_storage"
      },
      "t_mapping(t_address,t_struct(UnripeSettings)472_storage)": {
        "encoding": "mapping",
        "key": "t_address",
        "label": "mapping(address => struct Storage.UnripeSettings)",
        "numberOfBytes": "32",
        "value": "t_struct(UnripeSettings)472_storage"
      },
      "t_mapping(t_address,t_uint256)": {
        "encoding": "mapping",
        "key": "t_address",
        "label": "mapping(address => uint256)",
        "numberOfBytes": "32",
        "value": "t_uint256"
      },
      "t_mapping(t_bytes32,t_uint256)": {
        "encoding": "mapping",
        "key": "t_bytes32",
        "label": "mapping(bytes32 => uint256)",
        "numberOfBytes": "32",
        "value": "t_uint256"
      },
      "t_mapping(t_contract(IERC20)77,t_uint256)": {
        "encoding": "mapping",
        "key": "t_contract(IERC20)77",
        "label": "mapping(contract IERC20 => uint256)",
        "numberOfBytes": "32",
        "value": "t_uint256"
      },
      "t_mapping(t_uint128,t_uint128)": {
        "encoding": "mapping",
        "key": "t_uint128",
        "label": "mapping(uint128 => uint128)",
        "numberOfBytes": "32",
        "value": "t_uint128"
      },
      "t_mapping(t_uint128,t_uint256)": {
        "encoding": "mapping",
        "key": "t_uint128",
        "label": "mapping(uint128 => uint256)",
        "numberOfBytes": "32",
        "value": "t_uint256"
      },
      "t_mapping(t_uint256,t_bytes32)": {
        "encoding": "mapping",
        "key": "t_uint256",
        "label": "mapping(uint256 => bytes32)",
        "numberOfBytes": "32",
        "value": "t_bytes32"
      },
      "t_mapping(t_uint256,t_struct(Deposit)151_storage)": {
        "encoding": "mapping",
        "key": "t_uint256",
        "label": "mapping(uint256 => struct Account.Deposit)",
        "numberOfBytes": "32",
        "value": "t_struct(Deposit)151_storage"
      },
      "t_mapping(t_uint256,t_uint256)": {
        "encoding": "mapping",
        "key": "t_uint256",
        "label": "mapping(uint256 => uint256)",
        "numberOfBytes": "32",
        "value": "t_uint256"
      },
      "t_mapping(t_uint32,t_mapping(t_address,t_bool))": {
        "encoding": "mapping",
        "key": "t_uint32",
        "label": "mapping(uint32 => mapping(address => bool))",
        "numberOfBytes": "32",
        "value": "t_mapping(t_address,t_bool)"
      },
      "t_mapping(t_uint32,t_struct(Bip)305_storage)": {
        "encoding": "mapping",
        "key": "t_uint32",
        "label": "mapping(uint32 => struct Storage.Bip)",
        "numberOfBytes": "32",
        "value": "t_struct(Bip)305_storage"
      },
      "t_mapping(t_uint32,t_struct(Deposit)151_storage)": {
        "encoding": "mapping",
        "key": "t_uint32",
        "label": "mapping(uint32 => struct Account.Deposit)",
        "numberOfBytes": "32",
        "value": "t_struct(Deposit)151_storage"
      },
      "t_mapping(t_uint32,t_struct(DiamondCut)315_storage)": {
        "encoding": "mapping",
        "key": "t_uint32",
        "label": "mapping(uint32 => struct Storage.DiamondCut)",
        "numberOfBytes": "32",
        "value": "t_struct(DiamondCut)315_storage"
      },
      "t_mapping(t_uint32,t_struct(Fundraiser)440_storage)": {
        "encoding": "mapping",
        "key": "t_uint32",
        "label": "mapping(uint32 => struct Storage.Fundraiser)",
        "numberOfBytes": "32",
        "value": "t_struct(Fundraiser)440_storage"
      },
      "t_mapping(t_uint32,t_struct(Sr)502_storage)": {
        "encoding": "mapping",
        "key": "t_uint32",
        "label": "mapping(uint32 => struct Storage.Sr)",
        "numberOfBytes": "32",
        "value": "t_struct(Sr)502_storage"
      },
      "t_mapping(t_uint32,t_uint256)": {
        "encoding": "mapping",
        "key": "t_uint32",
        "label": "mapping(uint32 => uint256)",
        "numberOfBytes": "32",
        "value": "t_uint256"
      },
      "t_struct(AppStorage)684_storage": {
        "encoding": "inplace",
        "label": "struct AppStorage",
        "members": [
          {
            "astId": 506,
            "contract": "contracts/1_Storage.sol:Account",
            "label": "deprecated_index",
            "offset": 0,
            "slot": "0",
            "type": "t_uint8"
          },
          {
            "astId": 510,
            "contract": "contracts/1_Storage.sol:Account",
            "label": "deprecated_cases",
            "offset": 0,
            "slot": "1",
            "type": "t_array(t_int8)32_storage"
          },
          {
            "astId": 512,
            "contract": "contracts/1_Storage.sol:Account",
            "label": "paused",
            "offset": 0,
            "slot": "2",
            "type": "t_bool"
          },
          {
            "astId": 514,
            "contract": "contracts/1_Storage.sol:Account",
            "label": "pausedAt",
            "offset": 1,
            "slot": "2",
            "type": "t_uint128"
          },
          {
            "astId": 517,
            "contract": "contracts/1_Storage.sol:Account",
            "label": "season",
            "offset": 0,
            "slot": "3",
            "type": "t_struct(Season)414_storage"
          },
          {
            "astId": 520,
            "contract": "contracts/1_Storage.sol:Account",
            "label": "c",
            "offset": 0,
            "slot": "7",
            "type": "t_struct(Contracts)275_storage"
          },
          {
            "astId": 523,
            "contract": "contracts/1_Storage.sol:Account",
            "label": "f",
            "offset": 0,
            "slot": "11",
            "type": "t_struct(Field)287_storage"
          },
          {
            "astId": 526,
            "contract": "contracts/1_Storage.sol:Account",
            "label": "g",
            "offset": 0,
            "slot": "15",
            "type": "t_struct(Governance)338_storage"
          },
          {
            "astId": 529,
            "contract": "contracts/1_Storage.sol:Account",
            "label": "co",
            "offset": 0,
            "slot": "20",
            "type": "t_struct(CurveMetapoolOracle)376_storage"
          },
          {
            "astId": 532,
            "contract": "contracts/1_Storage.sol:Account",
            "label": "r",
            "offset": 0,
            "slot": "24",
            "type": "t_struct(Rain)384_storage"
          },
          {
            "astId": 535,
            "contract": "contracts/1_Storage.sol:Account",
            "label": "s",
            "offset": 0,
            "slot": "27",
            "type": "t_struct(Silo)364_storage"
          },
          {
            "astId": 537,
            "contract": "contracts/1_Storage.sol:Account",
            "label": "reentrantStatus",
            "offset": 0,
            "slot": "30",
            "type": "t_uint256"
          },
          {
            "astId": 540,
            "contract": "contracts/1_Storage.sol:Account",
            "label": "w",
            "offset": 0,
            "slot": "31",
            "type": "t_struct(Weather)428_storage"
          },
          {
            "astId": 542,
            "contract": "contracts/1_Storage.sol:Account",
            "label": "earnedBeans",
            "offset": 0,
            "slot": "34",
            "type": "t_uint256"
          },
          {
            "astId": 546,
            "contract": "contracts/1_Storage.sol:Account",
            "label": "deprecated",
            "offset": 0,
            "slot": "35",
            "type": "t_array(t_uint256)14_storage"
          },
          {
            "astId": 551,
            "contract": "contracts/1_Storage.sol:Account",
            "label": "a",
            "offset": 0,
            "slot": "49",
            "type": "t_mapping(t_address,t_struct(State)263_storage)"
          },
          {
            "astId": 553,
            "contract": "contracts/1_Storage.sol:Account",
            "label": "deprecated_bip0Start",
            "offset": 0,
            "slot": "50",
            "type": "t_uint32"
          },
          {
            "astId": 555,
            "contract": "contracts/1_Storage.sol:Account",
            "label": "deprecated_hotFix3Start",
            "offset": 4,
            "slot": "50",
            "type": "t_uint32"
          },
          {
            "astId": 560,
            "contract": "contracts/1_Storage.sol:Account",
            "label": "fundraisers",
            "offset": 0,
            "slot": "51",
            "type": "t_mapping(t_uint32,t_struct(Fundraiser)440_storage)"
          },
          {
            "astId": 562,
            "contract": "contracts/1_Storage.sol:Account",
            "label": "fundraiserIndex",
            "offset": 0,
            "slot": "52",
            "type": "t_uint32"
          },
          {
            "astId": 566,
            "contract": "contracts/1_Storage.sol:Account",
            "label": "deprecated_isBudget",
            "offset": 0,
            "slot": "53",
            "type": "t_mapping(t_address,t_bool)"
          },
          {
            "astId": 570,
            "contract": "contracts/1_Storage.sol:Account",
            "label": "podListings",
            "offset": 0,
            "slot": "54",
            "type": "t_mapping(t_uint256,t_bytes32)"
          },
          {
            "astId": 574,
            "contract": "contracts/1_Storage.sol:Account",
            "label": "podOrders",
            "offset": 0,
            "slot": "55",
            "type": "t_mapping(t_bytes32,t_uint256)"
          },
          {
            "astId": 579,
            "contract": "contracts/1_Storage.sol:Account",
            "label": "siloBalances",
            "offset": 0,
            "slot": "56",
            "type": "t_mapping(t_address,t_struct(AssetSilo)346_storage)"
          },
          {
            "astId": 584,
            "contract": "contracts/1_Storage.sol:Account",
            "label": "ss",
            "offset": 0,
            "slot": "57",
            "type": "t_mapping(t_address,t_struct(SiloSettings)464_storage)"
          },
          {
            "astId": 588,
            "contract": "contracts/1_Storage.sol:Account",
            "label": "deprecated2",
            "offset": 0,
            "slot": "58",
            "type": "t_array(t_uint256)2_storage"
          },
          {
            "astId": 590,
            "contract": "contracts/1_Storage.sol:Account",
            "label": "deprecated_newEarnedStalk",
            "offset": 0,
            "slot": "60",
            "type": "t_uint128"
          },
          {
            "astId": 592,
            "contract": "contracts/1_Storage.sol:Account",
            "label": "deprecated_vestingPeriodRoots",
            "offset": 16,
            "slot": "60",
            "type": "t_uint128"
          },
          {
            "astId": 596,
            "contract": "contracts/1_Storage.sol:Account",
            "label": "sops",
            "offset": 0,
            "slot": "61",
            "type": "t_mapping(t_uint32,t_uint256)"
          },
          {
            "astId": 603,
            "contract": "contracts/1_Storage.sol:Account",
            "label": "internalTokenBalance",
            "offset": 0,
            "slot": "62",
            "type": "t_mapping(t_address,t_mapping(t_contract(IERC20)77,t_uint256))"
          },
          {
            "astId": 609,
            "contract": "contracts/1_Storage.sol:Account",
            "label": "unripeClaimed",
            "offset": 0,
            "slot": "63",
            "type": "t_mapping(t_address,t_mapping(t_address,t_bool))"
          },
          {
            "astId": 614,
            "contract": "contracts/1_Storage.sol:Account",
            "label": "u",
            "offset": 0,
            "slot": "64",
            "type": "t_mapping(t_address,t_struct(UnripeSettings)472_storage)"
          },
          {
            "astId": 618,
            "contract": "contracts/1_Storage.sol:Account",
            "label": "fertilizer",
            "offset": 0,
            "slot": "65",
            "type": "t_mapping(t_uint128,t_uint256)"
          },
          {
            "astId": 622,
            "contract": "contracts/1_Storage.sol:Account",
            "label": "nextFid",
            "offset": 0,
            "slot": "66",
            "type": "t_mapping(t_uint128,t_uint128)"
          },
          {
            "astId": 624,
            "contract": "contracts/1_Storage.sol:Account",
            "label": "activeFertilizer",
            "offset": 0,
            "slot": "67",
            "type": "t_uint256"
          },
          {
            "astId": 626,
            "contract": "contracts/1_Storage.sol:Account",
            "label": "fertilizedIndex",
            "offset": 0,
            "slot": "68",
            "type": "t_uint256"
          },
          {
            "astId": 628,
            "contract": "contracts/1_Storage.sol:Account",
            "label": "unfertilizedIndex",
            "offset": 0,
            "slot": "69",
            "type": "t_uint256"
          },
          {
            "astId": 630,
            "contract": "contracts/1_Storage.sol:Account",
            "label": "fFirst",
            "offset": 0,
            "slot": "70",
            "type": "t_uint128"
          },
          {
            "astId": 632,
            "contract": "contracts/1_Storage.sol:Account",
            "label": "fLast",
            "offset": 16,
            "slot": "70",
            "type": "t_uint128"
          },
          {
            "astId": 634,
            "contract": "contracts/1_Storage.sol:Account",
            "label": "bpf",
            "offset": 0,
            "slot": "71",
            "type": "t_uint128"
          },
          {
            "astId": 636,
            "contract": "contracts/1_Storage.sol:Account",
            "label": "recapitalized",
            "offset": 0,
            "slot": "72",
            "type": "t_uint256"
          },
          {
            "astId": 638,
            "contract": "contracts/1_Storage.sol:Account",
            "label": "isFarm",
            "offset": 0,
            "slot": "73",
            "type": "t_uint256"
          },
          {
            "astId": 640,
            "contract": "contracts/1_Storage.sol:Account",
            "label": "ownerCandidate",
            "offset": 0,
            "slot": "74",
            "type": "t_address"
          },
          {
            "astId": 644,
            "contract": "contracts/1_Storage.sol:Account",
            "label": "wellOracleSnapshots",
            "offset": 0,
            "slot": "75",
            "type": "t_mapping(t_address,t_bytes_storage)"
          },
          {
            "astId": 646,
            "contract": "contracts/1_Storage.sol:Account",
            "label": "deprecated_beanEthPrice",
            "offset": 0,
            "slot": "76",
            "type": "t_uint256"
          },
          {
            "astId": 650,
            "contract": "contracts/1_Storage.sol:Account",
            "label": "migratedBdvs",
            "offset": 0,
            "slot": "77",
            "type": "t_mapping(t_address,t_uint256)"
          },
          {
            "astId": 655,
            "contract": "contracts/1_Storage.sol:Account",
            "label": "twaReserves",
            "offset": 0,
            "slot": "78",
            "type": "t_mapping(t_address,t_struct(TwaReserves)484_storage)"
          },
          {
            "astId": 659,
            "contract": "contracts/1_Storage.sol:Account",
            "label": "usdTokenPrice",
            "offset": 0,
            "slot": "79",
            "type": "t_mapping(t_address,t_uint256)"
          },
          {
            "astId": 662,
            "contract": "contracts/1_Storage.sol:Account",
            "label": "seedGauge",
            "offset": 0,
            "slot": "80",
            "type": "t_struct(SeedGauge)478_storage"
          },
          {
            "astId": 666,
            "contract": "contracts/1_Storage.sol:Account",
            "label": "casesV2",
            "offset": 0,
            "slot": "81",
            "type": "t_array(t_bytes32)144_storage"
          },
          {
            "astId": 669,
            "contract": "contracts/1_Storage.sol:Account",
            "label": "oddGerminating",
            "offset": 0,
            "slot": "225",
            "type": "t_struct(TotalGerminating)497_storage"
          },
          {
            "astId": 672,
            "contract": "contracts/1_Storage.sol:Account",
            "label": "evenGerminating",
            "offset": 0,
            "slot": "226",
            "type": "t_struct(TotalGerminating)497_storage"
          },
          {
            "astId": 677,
            "contract": "contracts/1_Storage.sol:Account",
            "label": "unclaimedGerminating",
            "offset": 0,
            "slot": "227",
            "type": "t_mapping(t_uint32,t_struct(Sr)502_storage)"
          },
          {
            "astId": 681,
            "contract": "contracts/1_Storage.sol:Account",
            "label": "whitelistStatuses",
            "offset": 0,
            "slot": "228",
            "type": "t_array(t_struct(WhitelistStatus)356_storage)dyn_storage"
          },
          {
            "astId": 683,
            "contract": "contracts/1_Storage.sol:Account",
            "label": "sopWell",
            "offset": 0,
            "slot": "229",
            "type": "t_address"
          }
        ],
        "numberOfBytes": "7360"
      },
      "t_struct(AssetSilo)145_storage": {
        "encoding": "inplace",
        "label": "struct Account.AssetSilo",
        "members": [
          {
            "astId": 136,
            "contract": "contracts/1_Storage.sol:Account",
            "label": "withdrawals",
            "offset": 0,
            "slot": "0",
            "type": "t_mapping(t_uint32,t_uint256)"
          },
          {
            "astId": 140,
            "contract": "contracts/1_Storage.sol:Account",
            "label": "deposits",
            "offset": 0,
            "slot": "1",
            "type": "t_mapping(t_uint32,t_uint256)"
          },
          {
            "astId": 144,
            "contract": "contracts/1_Storage.sol:Account",
            "label": "depositSeeds",
            "offset": 0,
            "slot": "2",
            "type": "t_mapping(t_uint32,t_uint256)"
          }
        ],
        "numberOfBytes": "96"
      },
      "t_struct(AssetSilo)346_storage": {
        "encoding": "inplace",
        "label": "struct Storage.AssetSilo",
        "members": [
          {
            "astId": 341,
            "contract": "contracts/1_Storage.sol:Account",
            "label": "deposited",
            "offset": 0,
            "slot": "0",
            "type": "t_uint128"
          },
          {
            "astId": 343,
            "contract": "contracts/1_Storage.sol:Account",
            "label": "depositedBdv",
            "offset": 16,
            "slot": "0",
            "type": "t_uint128"
          },
          {
            "astId": 345,
            "contract": "contracts/1_Storage.sol:Account",
            "label": "withdrawn",
            "offset": 0,
            "slot": "1",
            "type": "t_uint256"
          }
        ],
        "numberOfBytes": "64"
      },
      "t_struct(Bip)305_storage": {
        "encoding": "inplace",
        "label": "struct Storage.Bip",
        "members": [
          {
            "astId": 290,
            "contract": "contracts/1_Storage.sol:Account",
            "label": "proposer",
            "offset": 0,
            "slot": "0",
            "type": "t_address"
          },
          {
            "astId": 292,
            "contract": "contracts/1_Storage.sol:Account",
            "label": "start",
            "offset": 20,
            "slot": "0",
            "type": "t_uint32"
          },
          {
            "astId": 294,
            "contract": "contracts/1_Storage.sol:Account",
            "label": "period",
            "offset": 24,
            "slot": "0",
            "type": "t_uint32"
          },
          {
            "astId": 296,
            "contract": "contracts/1_Storage.sol:Account",
            "label": "executed",
            "offset": 28,
            "slot": "0",
            "type": "t_bool"
          },
          {
            "astId": 298,
            "contract": "contracts/1_Storage.sol:Account",
            "label": "pauseOrUnpause",
            "offset": 0,
            "slot": "1",
            "type": "t_int256"
          },
          {
            "astId": 300,
            "contract": "contracts/1_Storage.sol:Account",
            "label": "timestamp",
            "offset": 0,
            "slot": "2",
            "type": "t_uint128"
          },
          {
            "astId": 302,
            "contract": "contracts/1_Storage.sol:Account",
            "label": "roots",
            "offset": 0,
            "slot": "3",
            "type": "t_uint256"
          },
          {
            "astId": 304,
            "contract": "contracts/1_Storage.sol:Account",
            "label": "endTotalRoots",
            "offset": 0,
            "slot": "4",
            "type": "t_uint256"
          }
        ],
        "numberOfBytes": "160"
      },
      "t_struct(Contracts)275_storage": {
        "encoding": "inplace",
        "label": "struct Storage.Contracts",
        "members": [
          {
            "astId": 268,
            "contract": "contracts/1_Storage.sol:Account",
            "label": "bean",
            "offset": 0,
            "slot": "0",
            "type": "t_address"
          },
          {
            "astId": 270,
            "contract": "contracts/1_Storage.sol:Account",
            "label": "pair",
            "offset": 0,
            "slot": "1",
            "type": "t_address"
          },
          {
            "astId": 272,
            "contract": "contracts/1_Storage.sol:Account",
            "label": "pegPair",
            "offset": 0,
            "slot": "2",
            "type": "t_address"
          },
          {
            "astId": 274,
            "contract": "contracts/1_Storage.sol:Account",
            "label": "weth",
            "offset": 0,
            "slot": "3",
            "type": "t_address"
          }
        ],
        "numberOfBytes": "128"
      },
      "t_struct(CurveMetapoolOracle)376_storage": {
        "encoding": "inplace",
        "label": "struct Storage.CurveMetapoolOracle",
        "members": [
          {
            "astId": 367,
            "contract": "contracts/1_Storage.sol:Account",
            "label": "initialized",
            "offset": 0,
            "slot": "0",
            "type": "t_bool"
          },
          {
            "astId": 369,
            "contract": "contracts/1_Storage.sol:Account",
            "label": "startSeason",
            "offset": 1,
            "slot": "0",
            "type": "t_uint32"
          },
          {
            "astId": 373,
            "contract": "contracts/1_Storage.sol:Account",
            "label": "balances",
            "offset": 0,
            "slot": "1",
            "type": "t_array(t_uint256)2_storage"
          },
          {
            "astId": 375,
            "contract": "contracts/1_Storage.sol:Account",
            "label": "timestamp",
            "offset": 0,
            "slot": "3",
            "type": "t_uint256"
          }
        ],
        "numberOfBytes": "128"
      },
      "t_struct(Deposit)151_storage": {
        "encoding": "inplace",
        "label": "struct Account.Deposit",
        "members": [
          {
            "astId": 148,
            "contract": "contracts/1_Storage.sol:Account",
            "label": "amount",
            "offset": 0,
            "slot": "0",
            "type": "t_uint128"
          },
          {
            "astId": 150,
            "contract": "contracts/1_Storage.sol:Account",
            "label": "bdv",
            "offset": 16,
            "slot": "0",
            "type": "t_uint128"
          }
        ],
        "numberOfBytes": "32"
      },
      "t_struct(Deposited)490_storage": {
        "encoding": "inplace",
        "label": "struct Storage.Deposited",
        "members": [
          {
            "astId": 487,
            "contract": "contracts/1_Storage.sol:Account",
            "label": "amount",
            "offset": 0,
            "slot": "0",
            "type": "t_uint128"
          },
          {
            "astId": 489,
            "contract": "contracts/1_Storage.sol:Account",
            "label": "bdv",
            "offset": 16,
            "slot": "0",
            "type": "t_uint128"
          }
        ],
        "numberOfBytes": "32"
      },
      "t_struct(DiamondCut)315_storage": {
        "encoding": "inplace",
        "label": "struct Storage.DiamondCut",
        "members": [
          {
            "astId": 310,
            "contract": "contracts/1_Storage.sol:Account",
            "label": "diamondCut",
            "offset": 0,
            "slot": "0",
            "type": "t_array(t_struct(FacetCut)91_storage)dyn_storage"
          },
          {
            "astId": 312,
            "contract": "contracts/1_Storage.sol:Account",
            "label": "initAddress",
            "offset": 0,
            "slot": "1",
            "type": "t_address"
          },
          {
            "astId": 314,
            "contract": "contracts/1_Storage.sol:Account",
            "label": "initData",
            "offset": 0,
            "slot": "2",
            "type": "t_bytes_storage"
          }
        ],
        "numberOfBytes": "96"
      },
      "t_struct(FacetCut)91_storage": {
        "encoding": "inplace",
        "label": "struct IDiamondCut.FacetCut",
        "members": [
          {
            "astId": 84,
            "contract": "contracts/1_Storage.sol:Account",
            "label": "facetAddress",
            "offset": 0,
            "slot": "0",
            "type": "t_address"
          },
          {
            "astId": 87,
            "contract": "contracts/1_Storage.sol:Account",
            "label": "action",
            "offset": 20,
            "slot": "0",
            "type": "t_enum(FacetCutAction)82"
          },
          {
            "astId": 90,
            "contract": "contracts/1_Storage.sol:Account",
            "label": "functionSelectors",
            "offset": 0,
            "slot": "1",
            "type": "t_array(t_bytes4)dyn_storage"
          }
        ],
        "numberOfBytes": "64"
      },
      "t_struct(FarmerGerminatingStalk)163_storage": {
        "encoding": "inplace",
        "label": "struct Account.FarmerGerminatingStalk",
        "members": [
          {
            "astId": 160,
            "contract": "contracts/1_Storage.sol:Account",
            "label": "odd",
            "offset": 0,
            "slot": "0",
            "type": "t_uint128"
          },
          {
            "astId": 162,
            "contract": "contracts/1_Storage.sol:Account",
            "label": "even",
            "offset": 16,
            "slot": "0",
            "type": "t_uint128"
          }
        ],
        "numberOfBytes": "32"
      },
      "t_struct(Field)131_storage": {
        "encoding": "inplace",
        "label": "struct Account.Field",
        "members": [
          {
            "astId": 126,
            "contract": "contracts/1_Storage.sol:Account",
            "label": "plots",
            "offset": 0,
            "slot": "0",
            "type": "t_mapping(t_uint256,t_uint256)"
          },
          {
            "astId": 130,
            "contract": "contracts/1_Storage.sol:Account",
            "label": "podAllowances",
            "offset": 0,
            "slot": "1",
            "type": "t_mapping(t_address,t_uint256)"
          }
        ],
        "numberOfBytes": "64"
      },
      "t_struct(Field)287_storage": {
        "encoding": "inplace",
        "label": "struct Storage.Field",
        "members": [
          {
            "astId": 278,
            "contract": "contracts/1_Storage.sol:Account",
            "label": "soil",
            "offset": 0,
            "slot": "0",
            "type": "t_uint128"
          },
          {
            "astId": 280,
            "contract": "contracts/1_Storage.sol:Account",
            "label": "beanSown",
            "offset": 16,
            "slot": "0",
            "type": "t_uint128"
          },
          {
            "astId": 282,
            "contract": "contracts/1_Storage.sol:Account",
            "label": "pods",
            "offset": 0,
            "slot": "1",
            "type": "t_uint256"
          },
          {
            "astId": 284,
            "contract": "contracts/1_Storage.sol:Account",
            "label": "harvested",
            "offset": 0,
            "slot": "2",
            "type": "t_uint256"
          },
          {
            "astId": 286,
            "contract": "contracts/1_Storage.sol:Account",
            "label": "harvestable",
            "offset": 0,
            "slot": "3",
            "type": "t_uint256"
          }
        ],
        "numberOfBytes": "128"
      },
      "t_struct(Fundraiser)440_storage": {
        "encoding": "inplace",
        "label": "struct Storage.Fundraiser",
        "members": [
          {
            "astId": 431,
            "contract": "contracts/1_Storage.sol:Account",
            "label": "payee",
            "offset": 0,
            "slot": "0",
            "type": "t_address"
          },
          {
            "astId": 433,
            "contract": "contracts/1_Storage.sol:Account",
            "label": "token",
            "offset": 0,
            "slot": "1",
            "type": "t_address"
          },
          {
            "astId": 435,
            "contract": "contracts/1_Storage.sol:Account",
            "label": "total",
            "offset": 0,
            "slot": "2",
            "type": "t_uint256"
          },
          {
            "astId": 437,
            "contract": "contracts/1_Storage.sol:Account",
            "label": "remaining",
            "offset": 0,
            "slot": "3",
            "type": "t_uint256"
          },
          {
            "astId": 439,
            "contract": "contracts/1_Storage.sol:Account",
            "label": "start",
            "offset": 0,
            "slot": "4",
            "type": "t_uint256"
          }
        ],
        "numberOfBytes": "160"
      },
      "t_struct(Governance)338_storage": {
        "encoding": "inplace",
        "label": "struct Storage.Governance",
        "members": [
          {
            "astId": 319,
            "contract": "contracts/1_Storage.sol:Account",
            "label": "activeBips",
            "offset": 0,
            "slot": "0",
            "type": "t_array(t_uint32)dyn_storage"
          },
          {
            "astId": 321,
            "contract": "contracts/1_Storage.sol:Account",
            "label": "bipIndex",
            "offset": 0,
            "slot": "1",
            "type": "t_uint32"
          },
          {
            "astId": 326,
            "contract": "contracts/1_Storage.sol:Account",
            "label": "diamondCuts",
            "offset": 0,
            "slot": "2",
            "type": "t_mapping(t_uint32,t_struct(DiamondCut)315_storage)"
          },
          {
            "astId": 332,
            "contract": "contracts/1_Storage.sol:Account",
            "label": "voted",
            "offset": 0,
            "slot": "3",
            "type": "t_mapping(t_uint32,t_mapping(t_address,t_bool))"
          },
          {
            "astId": 337,
            "contract": "contracts/1_Storage.sol:Account",
            "label": "bips",
            "offset": 0,
            "slot": "4",
            "type": "t_mapping(t_uint32,t_struct(Bip)305_storage)"
          }
        ],
        "numberOfBytes": "160"
      },
      "t_struct(MowStatus)169_storage": {
        "encoding": "inplace",
        "label": "struct Account.MowStatus",
        "members": [
          {
            "astId": 166,
            "contract": "contracts/1_Storage.sol:Account",
            "label": "lastStem",
            "offset": 0,
            "slot": "0",
            "type": "t_int96"
          },
          {
            "astId": 168,
            "contract": "contracts/1_Storage.sol:Account",
            "label": "bdv",
            "offset": 12,
            "slot": "0",
            "type": "t_uint128"
          }
        ],
        "numberOfBytes": "32"
      },
      "t_struct(Rain)384_storage": {
        "encoding": "inplace",
        "label": "struct Storage.Rain",
        "members": [
          {
            "astId": 379,
            "contract": "contracts/1_Storage.sol:Account",
            "label": "deprecated",
            "offset": 0,
            "slot": "0",
            "type": "t_uint256"
          },
          {
            "astId": 381,
            "contract": "contracts/1_Storage.sol:Account",
            "label": "pods",
            "offset": 0,
            "slot": "1",
            "type": "t_uint256"
          },
          {
            "astId": 383,
            "contract": "contracts/1_Storage.sol:Account",
            "label": "roots",
            "offset": 0,
            "slot": "2",
            "type": "t_uint256"
          }
        ],
        "numberOfBytes": "96"
      },
      "t_struct(Season)414_storage": {
        "encoding": "inplace",
        "label": "struct Storage.Season",
        "members": [
          {
            "astId": 387,
            "contract": "contracts/1_Storage.sol:Account",
            "label": "current",
            "offset": 0,
            "slot": "0",
            "type": "t_uint32"
          },
          {
            "astId": 389,
            "contract": "contracts/1_Storage.sol:Account",
            "label": "lastSop",
            "offset": 4,
            "slot": "0",
            "type": "t_uint32"
          },
          {
            "astId": 391,
            "contract": "contracts/1_Storage.sol:Account",
            "label": "withdrawSeasons",
            "offset": 8,
            "slot": "0",
            "type": "t_uint8"
          },
          {
            "astId": 393,
            "contract": "contracts/1_Storage.sol:Account",
            "label": "lastSopSeason",
            "offset": 9,
            "slot": "0",
            "type": "t_uint32"
          },
          {
            "astId": 395,
            "contract": "contracts/1_Storage.sol:Account",
            "label": "rainStart",
            "offset": 13,
            "slot": "0",
            "type": "t_uint32"
          },
          {
            "astId": 397,
            "contract": "contracts/1_Storage.sol:Account",
            "label": "raining",
            "offset": 17,
            "slot": "0",
            "type": "t_bool"
          },
          {
            "astId": 399,
            "contract": "contracts/1_Storage.sol:Account",
            "label": "fertilizing",
            "offset": 18,
            "slot": "0",
            "type": "t_bool"
          },
          {
            "astId": 401,
            "contract": "contracts/1_Storage.sol:Account",
            "label": "sunriseBlock",
            "offset": 19,
            "slot": "0",
            "type": "t_uint32"
          },
          {
            "astId": 403,
            "contract": "contracts/1_Storage.sol:Account",
            "label": "abovePeg",
            "offset": 23,
            "slot": "0",
            "type": "t_bool"
          },
          {
            "astId": 405,
            "contract": "contracts/1_Storage.sol:Account",
            "label": "stemStartSeason",
            "offset": 24,
            "slot": "0",
            "type": "t_uint16"
          },
          {
            "astId": 407,
            "contract": "contracts/1_Storage.sol:Account",
            "label": "stemScaleSeason",
            "offset": 26,
            "slot": "0",
            "type": "t_uint16"
          },
          {
            "astId": 409,
            "contract": "contracts/1_Storage.sol:Account",
            "label": "start",
            "offset": 0,
            "slot": "1",
            "type": "t_uint256"
          },
          {
            "astId": 411,
            "contract": "contracts/1_Storage.sol:Account",
            "label": "period",
            "offset": 0,
            "slot": "2",
            "type": "t_uint256"
          },
          {
            "astId": 413,
            "contract": "contracts/1_Storage.sol:Account",
            "label": "timestamp",
            "offset": 0,
            "slot": "3",
            "type": "t_uint256"
          }
        ],
        "numberOfBytes": "128"
      },
      "t_struct(SeasonOfPlenty)177_storage": {
        "encoding": "inplace",
        "label": "struct Account.SeasonOfPlenty",
        "members": [
          {
            "astId": 172,
            "contract": "contracts/1_Storage.sol:Account",
            "label": "roots",
            "offset": 0,
            "slot": "0",
            "type": "t_uint256"
          },
          {
            "astId": 174,
            "contract": "contracts/1_Storage.sol:Account",
            "label": "plentyPerRoot",
            "offset": 0,
            "slot": "1",
            "type": "t_uint256"
          },
          {
            "astId": 176,
            "contract": "contracts/1_Storage.sol:Account",
            "label": "plenty",
            "offset": 0,
            "slot": "2",
            "type": "t_uint256"
          }
        ],
        "numberOfBytes": "96"
      },
      "t_struct(SeedGauge)478_storage": {
        "encoding": "inplace",
        "label": "struct Storage.SeedGauge",
        "members": [
          {
            "astId": 475,
            "contract": "contracts/1_Storage.sol:Account",
            "label": "averageGrownStalkPerBdvPerSeason",
            "offset": 0,
            "slot": "0",
            "type": "t_uint128"
          },
          {
            "astId": 477,
            "contract": "contracts/1_Storage.sol:Account",
            "label": "beanToMaxLpGpPerBdvRatio",
            "offset": 16,
            "slot": "0",
            "type": "t_uint128"
          }
        ],
        "numberOfBytes": "32"
      },
      "t_struct(Silo)157_storage": {
        "encoding": "inplace",
        "label": "struct Account.Silo",
        "members": [
          {
            "astId": 154,
            "contract": "contracts/1_Storage.sol:Account",
            "label": "stalk",
            "offset": 0,
            "slot": "0",
            "type": "t_uint256"
          },
          {
            "astId": 156,
            "contract": "contracts/1_Storage.sol:Account",
            "label": "seeds",
            "offset": 0,
            "slot": "1",
            "type": "t_uint256"
          }
        ],
        "numberOfBytes": "64"
      },
      "t_struct(Silo)364_storage": {
        "encoding": "inplace",
        "label": "struct Storage.Silo",
        "members": [
          {
            "astId": 359,
            "contract": "contracts/1_Storage.sol:Account",
            "label": "stalk",
            "offset": 0,
            "slot": "0",
            "type": "t_uint256"
          },
          {
            "astId": 361,
            "contract": "contracts/1_Storage.sol:Account",
            "label": "deprecated_seeds",
            "offset": 0,
            "slot": "1",
            "type": "t_uint256"
          },
          {
            "astId": 363,
            "contract": "contracts/1_Storage.sol:Account",
            "label": "roots",
            "offset": 0,
            "slot": "2",
            "type": "t_uint256"
          }
        ],
        "numberOfBytes": "96"
      },
      "t_struct(SiloSettings)464_storage": {
        "encoding": "inplace",
        "label": "struct Storage.SiloSettings",
        "members": [
          {
            "astId": 443,
            "contract": "contracts/1_Storage.sol:Account",
            "label": "selector",
            "offset": 0,
            "slot": "0",
            "type": "t_bytes4"
          },
          {
            "astId": 445,
            "contract": "contracts/1_Storage.sol:Account",
            "label": "stalkEarnedPerSeason",
            "offset": 4,
            "slot": "0",
            "type": "t_uint32"
          },
          {
            "astId": 447,
            "contract": "contracts/1_Storage.sol:Account",
            "label": "stalkIssuedPerBdv",
            "offset": 8,
            "slot": "0",
            "type": "t_uint32"
          },
          {
            "astId": 449,
            "contract": "contracts/1_Storage.sol:Account",
            "label": "milestoneSeason",
            "offset": 12,
            "slot": "0",
            "type": "t_uint32"
          },
          {
            "astId": 451,
            "contract": "contracts/1_Storage.sol:Account",
            "label": "milestoneStem",
            "offset": 16,
            "slot": "0",
            "type": "t_int96"
          },
          {
            "astId": 453,
            "contract": "contracts/1_Storage.sol:Account",
            "label": "encodeType",
            "offset": 28,
            "slot": "0",
            "type": "t_bytes1"
          },
          {
            "astId": 455,
            "contract": "contracts/1_Storage.sol:Account",
            "label": "deltaStalkEarnedPerSeason",
            "offset": 29,
            "slot": "0",
            "type": "t_int24"
          },
          {
            "astId": 457,
            "contract": "contracts/1_Storage.sol:Account",
            "label": "gpSelector",
            "offset": 0,
            "slot": "1",
            "type": "t_bytes4"
          },
          {
            "astId": 459,
            "contract": "contracts/1_Storage.sol:Account",
            "label": "lwSelector",
            "offset": 4,
            "slot": "1",
            "type": "t_bytes4"
          },
          {
            "astId": 461,
            "contract": "contracts/1_Storage.sol:Account",
            "label": "gaugePoints",
            "offset": 8,
            "slot": "1",
            "type": "t_uint128"
          },
          {
            "astId": 463,
            "contract": "contracts/1_Storage.sol:Account",
            "label": "optimalPercentDepositedBdv",
            "offset": 24,
            "slot": "1",
            "type": "t_uint64"
          }
        ],
        "numberOfBytes": "64"
      },
      "t_struct(Sr)502_storage": {
        "encoding": "inplace",
        "label": "struct Storage.Sr",
        "members": [
          {
            "astId": 499,
            "contract": "contracts/1_Storage.sol:Account",
            "label": "stalk",
            "offset": 0,
            "slot": "0",
            "type": "t_uint128"
          },
          {
            "astId": 501,
            "contract": "contracts/1_Storage.sol:Account",
            "label": "roots",
            "offset": 16,
            "slot": "0",
            "type": "t_uint128"
          }
        ],
        "numberOfBytes": "32"
      },
      "t_struct(State)263_storage": {
        "encoding": "inplace",
        "label": "struct Account.State",
        "members": [
          {
            "astId": 181,
            "contract": "contracts/1_Storage.sol:Account",
            "label": "field",
            "offset": 0,
            "slot": "0",
            "type": "t_struct(Field)131_storage"
          },
          {
            "astId": 184,
            "contract": "contracts/1_Storage.sol:Account",
            "label": "bean",
            "offset": 0,
            "slot": "2",
            "type": "t_struct(AssetSilo)145_storage"
          },
          {
            "astId": 187,
            "contract": "contracts/1_Storage.sol:Account",
            "label": "lp",
            "offset": 0,
            "slot": "5",
            "type": "t_struct(AssetSilo)145_storage"
          },
          {
            "astId": 190,
            "contract": "contracts/1_Storage.sol:Account",
            "label": "s",
            "offset": 0,
            "slot": "8",
            "type": "t_struct(Silo)157_storage"
          },
          {
            "astId": 192,
            "contract": "contracts/1_Storage.sol:Account",
            "label": "votedUntil",
            "offset": 0,
            "slot": "10",
            "type": "t_uint32"
          },
          {
            "astId": 194,
            "contract": "contracts/1_Storage.sol:Account",
            "label": "lastUpdate",
            "offset": 4,
            "slot": "10",
            "type": "t_uint32"
          },
          {
            "astId": 196,
            "contract": "contracts/1_Storage.sol:Account",
            "label": "lastSop",
            "offset": 8,
            "slot": "10",
            "type": "t_uint32"
          },
          {
            "astId": 198,
            "contract": "contracts/1_Storage.sol:Account",
            "label": "lastRain",
            "offset": 12,
            "slot": "10",
            "type": "t_uint32"
          },
          {
            "astId": 200,
            "contract": "contracts/1_Storage.sol:Account",
            "label": "deprecated_deltaRoots",
            "offset": 16,
            "slot": "10",
            "type": "t_uint128"
          },
          {
            "astId": 203,
            "contract": "contracts/1_Storage.sol:Account",
            "label": "deprecated",
            "offset": 0,
            "slot": "11",
            "type": "t_struct(SeasonOfPlenty)177_storage"
          },
          {
            "astId": 205,
            "contract": "contracts/1_Storage.sol:Account",
            "label": "roots",
            "offset": 0,
            "slot": "14",
            "type": "t_uint256"
          },
          {
            "astId": 207,
            "contract": "contracts/1_Storage.sol:Account",
            "label": "deprecated_wrappedBeans",
            "offset": 0,
            "slot": "15",
            "type": "t_uint256"
          },
          {
            "astId": 214,
            "contract": "contracts/1_Storage.sol:Account",
            "label": "legacyV2Deposits",
            "offset": 0,
            "slot": "16",
            "type": "t_mapping(t_address,t_mapping(t_uint32,t_struct(Deposit)151_storage))"
          },
          {
            "astId": 220,
            "contract": "contracts/1_Storage.sol:Account",
            "label": "withdrawals",
            "offset": 0,
            "slot": "17",
            "type": "t_mapping(t_address,t_mapping(t_uint32,t_uint256))"
          },
          {
            "astId": 223,
            "contract": "contracts/1_Storage.sol:Account",
            "label": "sop",
            "offset": 0,
            "slot": "18",
            "type": "t_struct(SeasonOfPlenty)177_storage"
          },
          {
            "astId": 229,
            "contract": "contracts/1_Storage.sol:Account",
            "label": "depositAllowances",
            "offset": 0,
            "slot": "21",
            "type": "t_mapping(t_address,t_mapping(t_address,t_uint256))"
          },
          {
            "astId": 236,
            "contract": "contracts/1_Storage.sol:Account",
            "label": "tokenAllowances",
            "offset": 0,
            "slot": "22",
            "type": "t_mapping(t_address,t_mapping(t_contract(IERC20)77,t_uint256))"
          },
          {
            "astId": 238,
            "contract": "contracts/1_Storage.sol:Account",
            "label": "depositPermitNonces",
            "offset": 0,
            "slot": "23",
            "type": "t_uint256"
          },
          {
            "astId": 240,
            "contract": "contracts/1_Storage.sol:Account",
            "label": "tokenPermitNonces",
            "offset": 0,
            "slot": "24",
            "type": "t_uint256"
          },
          {
            "astId": 245,
            "contract": "contracts/1_Storage.sol:Account",
            "label": "legacyV3Deposits",
            "offset": 0,
            "slot": "25",
            "type": "t_mapping(t_uint256,t_struct(Deposit)151_storage)"
          },
          {
            "astId": 250,
            "contract": "contracts/1_Storage.sol:Account",
            "label": "mowStatuses",
            "offset": 0,
            "slot": "26",
            "type": "t_mapping(t_address,t_struct(MowStatus)169_storage)"
          },
          {
            "astId": 254,
            "contract": "contracts/1_Storage.sol:Account",
            "label": "isApprovedForAll",
            "offset": 0,
            "slot": "27",
            "type": "t_mapping(t_address,t_bool)"
          },
          {
            "astId": 257,
            "contract": "contracts/1_Storage.sol:Account",
            "label": "farmerGerminating",
            "offset": 0,
            "slot": "28",
            "type": "t_struct(FarmerGerminatingStalk)163_storage"
          },
          {
            "astId": 262,
            "contract": "contracts/1_Storage.sol:Account",
            "label": "deposits",
            "offset": 0,
            "slot": "29",
            "type": "t_mapping(t_uint256,t_struct(Deposit)151_storage)"
          }
        ],
        "numberOfBytes": "960"
      },
      "t_struct(TotalGerminating)497_storage": {
        "encoding": "inplace",
        "label": "struct Storage.TotalGerminating",
        "members": [
          {
            "astId": 496,
            "contract": "contracts/1_Storage.sol:Account",
            "label": "deposited",
            "offset": 0,
            "slot": "0",
            "type": "t_mapping(t_address,t_struct(Deposited)490_storage)"
          }
        ],
        "numberOfBytes": "32"
      },
      "t_struct(TwaReserves)484_storage": {
        "encoding": "inplace",
        "label": "struct Storage.TwaReserves",
        "members": [
          {
            "astId": 481,
            "contract": "contracts/1_Storage.sol:Account",
            "label": "reserve0",
            "offset": 0,
            "slot": "0",
            "type": "t_uint128"
          },
          {
            "astId": 483,
            "contract": "contracts/1_Storage.sol:Account",
            "label": "reserve1",
            "offset": 16,
            "slot": "0",
            "type": "t_uint128"
          }
        ],
        "numberOfBytes": "32"
      },
      "t_struct(UnripeSettings)472_storage": {
        "encoding": "inplace",
        "label": "struct Storage.UnripeSettings",
        "members": [
          {
            "astId": 467,
            "contract": "contracts/1_Storage.sol:Account",
            "label": "underlyingToken",
            "offset": 0,
            "slot": "0",
            "type": "t_address"
          },
          {
            "astId": 469,
            "contract": "contracts/1_Storage.sol:Account",
            "label": "balanceOfUnderlying",
            "offset": 0,
            "slot": "1",
            "type": "t_uint256"
          },
          {
            "astId": 471,
            "contract": "contracts/1_Storage.sol:Account",
            "label": "merkleRoot",
            "offset": 0,
            "slot": "2",
            "type": "t_bytes32"
          }
        ],
        "numberOfBytes": "96"
      },
      "t_struct(Weather)428_storage": {
        "encoding": "inplace",
        "label": "struct Storage.Weather",
        "members": [
          {
            "astId": 419,
            "contract": "contracts/1_Storage.sol:Account",
            "label": "deprecated",
            "offset": 0,
            "slot": "0",
            "type": "t_array(t_uint256)2_storage"
          },
          {
            "astId": 421,
            "contract": "contracts/1_Storage.sol:Account",
            "label": "lastDSoil",
            "offset": 0,
            "slot": "2",
            "type": "t_uint128"
          },
          {
            "astId": 423,
            "contract": "contracts/1_Storage.sol:Account",
            "label": "lastSowTime",
            "offset": 16,
            "slot": "2",
            "type": "t_uint32"
          },
          {
            "astId": 425,
            "contract": "contracts/1_Storage.sol:Account",
            "label": "thisSowTime",
            "offset": 20,
            "slot": "2",
            "type": "t_uint32"
          },
          {
            "astId": 427,
            "contract": "contracts/1_Storage.sol:Account",
            "label": "t",
            "offset": 24,
            "slot": "2",
            "type": "t_uint32"
          }
        ],
        "numberOfBytes": "96"
      },
      "t_struct(WhitelistStatus)356_storage": {
        "encoding": "inplace",
        "label": "struct Storage.WhitelistStatus",
        "members": [
          {
            "astId": 349,
            "contract": "contracts/1_Storage.sol:Account",
            "label": "token",
            "offset": 0,
            "slot": "0",
            "type": "t_address"
          },
          {
            "astId": 351,
            "contract": "contracts/1_Storage.sol:Account",
            "label": "isWhitelisted",
            "offset": 20,
            "slot": "0",
            "type": "t_bool"
          },
          {
            "astId": 353,
            "contract": "contracts/1_Storage.sol:Account",
            "label": "isWhitelistedLp",
            "offset": 21,
            "slot": "0",
            "type": "t_bool"
          },
          {
            "astId": 355,
            "contract": "contracts/1_Storage.sol:Account",
            "label": "isWhitelistedWell",
            "offset": 22,
            "slot": "0",
            "type": "t_bool"
          }
        ],
        "numberOfBytes": "32"
      },
      "t_uint128": {
        "encoding": "inplace",
        "label": "uint128",
        "numberOfBytes": "16"
      },
      "t_uint16": {
        "encoding": "inplace",
        "label": "uint16",
        "numberOfBytes": "2"
      },
      "t_uint256": {
        "encoding": "inplace",
        "label": "uint256",
        "numberOfBytes": "32"
      },
      "t_uint32": {
        "encoding": "inplace",
        "label": "uint32",
        "numberOfBytes": "4"
      },
      "t_uint64": {
        "encoding": "inplace",
        "label": "uint64",
        "numberOfBytes": "8"
      },
      "t_uint8": {
        "encoding": "inplace",
        "label": "uint8",
        "numberOfBytes": "1"
      }
    }
  }